{"protocol":{"minReaderVersion":1,"minWriterVersion":2}}
{"metaData":{"id":"9a387db7-ad35-4089-b837-c17779b52470","format":{"provider":"parquet","options":{}},"schemaString":"{\"type\":\"struct\",\"fields\":[{\"name\":\"sandbox_field\",\"type\":\"string\",\"nullable\":true,\"metadata\":{}}]}","partitionColumns":[],"configuration":{},"createdTime":1668519022772}}
{"commitInfo":{"timestamp":1668519022969,"operation":"CREATE TABLE","operationParameters":{"isManaged":"false","description":null,"partitionBy":"[]","properties":"{}"},"isolationLevel":"Serializable","isBlindAppend":true,"operationMetrics":{},"engineInfo":"Apache-Spark/3.3.0 Delta-Lake/2.1.0","txnId":"8f069745-6962-445e-9100-98b8a33a7822"}}
